odoo10_addon_account_bank_statement_import_camt_details-10.0.1.0.1-py2.7-nspkg.pth
odoo/addons/account_bank_statement_import_camt_details/README.rst
odoo/addons/account_bank_statement_import_camt_details/__init__.py
odoo/addons/account_bank_statement_import_camt_details/__manifest__.py
odoo/addons/account_bank_statement_import_camt_details/i18n/account_bank_statement_import_camt_details.pot
odoo/addons/account_bank_statement_import_camt_details/models/__init__.py
odoo/addons/account_bank_statement_import_camt_details/models/account_bank_statement_line.py
odoo/addons/account_bank_statement_import_camt_details/models/camt_parser.py
odoo/addons/account_bank_statement_import_camt_details/static/description/icon.png
odoo/addons/account_bank_statement_import_camt_details/static/src/xml/camt_details_reconciliation_layout.xml
odoo/addons/account_bank_statement_import_camt_details/tests/__init__.py
odoo/addons/account_bank_statement_import_camt_details/tests/test_import_bank_statement.py
odoo/addons/account_bank_statement_import_camt_details/views/account_bank_statement_line.xml
odoo10_addon_account_bank_statement_import_camt_details-10.0.1.0.1.dist-info/METADATA
odoo10_addon_account_bank_statement_import_camt_details-10.0.1.0.1.dist-info/RECORD
odoo10_addon_account_bank_statement_import_camt_details-10.0.1.0.1.dist-info/WHEEL
odoo10_addon_account_bank_statement_import_camt_details-10.0.1.0.1.dist-info/namespace_packages.txt
odoo10_addon_account_bank_statement_import_camt_details-10.0.1.0.1.dist-info/top_level.txt
